biobroker/__init__.py
biobroker/requirements.txt
biobroker/api/README.md
biobroker/api/__init__.py
biobroker/api/api.py
biobroker/api/exceptions.py
biobroker/authenticator/__init__.py
biobroker/authenticator/authenticator.py
biobroker/authenticator/exceptions.py
biobroker/generic/__init__.py
biobroker/generic/exceptions.py
biobroker/generic/logger.py
biobroker/generic/pydantic_model.py
biobroker/generic/utilities.py
biobroker/input_processor/README.md
biobroker/input_processor/__init__.py
biobroker/input_processor/exceptions.py
biobroker/input_processor/input_processor.py
biobroker/metadata_entity/README.md
biobroker/metadata_entity/__init__.py
biobroker/metadata_entity/exceptions.py
biobroker/metadata_entity/metadata_entity.py
biobroker/output_processor/__init__.py
biobroker/output_processor/output_processor.py
biobroker/wrangler/__init__.py
biobroker/wrangler/exceptions.py
biobroker/wrangler/wrangler.py
biobroker-0.1.1.dist-info/METADATA
biobroker-0.1.1.dist-info/WHEEL
biobroker-0.1.1.dist-info/licenses/LICENSE
biobroker-0.1.1.dist-info/RECORD
