Metadata-Version: 2.3
Name: biobroker
Version: 0.1.1
Summary: A package to easily broker data and metadata to repositories.
Project-URL: Documentation, https://biobroker.readthedocs.io/en/latest/
Project-URL: Repository, https://github.com/ESapenaVentura/biobroker.git
Project-URL: Issues, https://github.com/ESapenaVentura/biobroker/issues
Author-email: Enrique Sapena Ventura <sapenaventura@gmail.com>
Maintainer-email: Enrique Sapena Ventura <sapenaventura@gmail.com>
License:                     GNU GENERAL PUBLIC LICENSE
Keywords: Biosamples,Metadata,broker,brokering
Classifier: Development Status :: 4 - Beta
Requires-Python: >=3.10
Requires-Dist: numpy~=2.1.3
Requires-Dist: openpyxl==3.1.2
Requires-Dist: pandas~=2.2.3
Requires-Dist: progressbar2~=4.4.2
Requires-Dist: pydantic~=2.9.2
Requires-Dist: requests>=2.31.0
